chaosgremlin/__init__.py
chaosgremlin/actions.py
chaostoolkit_gremlin_yy-0.3.2.dist-info/METADATA
chaostoolkit_gremlin_yy-0.3.2.dist-info/RECORD
chaostoolkit_gremlin_yy-0.3.2.dist-info/WHEEL
chaostoolkit_gremlin_yy-0.3.2.dist-info/top_level.txt
