Metadata-Version: 2.1
Name: chaostoolkit-gremlin-yy
Version: 0.3.2
Summary: Chaos Toolkit Gremlin, YY. support
Home-page: https://github.com/beingcoder/chaostoolkit-gremlin
Author: chaostoolkit Team
Author-email: 1020828078@qq.com
License: Apache License Version 2.0
Platform: UNKNOWN
Classifier: Development Status :: 2 - Pre-Alpha
Classifier: Intended Audience :: Developers
Classifier: License :: Freely Distributable
Classifier: Operating System :: OS Independent
Classifier: License :: OSI Approved :: Apache Software License
Classifier: Programming Language :: Python
Classifier: Programming Language :: Python :: 3
Classifier: Programming Language :: Python :: 3.5
Classifier: Programming Language :: Python :: 3.6
Classifier: Programming Language :: Python :: Implementation
Classifier: Programming Language :: Python :: Implementation :: CPython
Requires-Python: >=3.5.*
Requires-Dist: chaostoolkit-lib (>=0.7.0)
Requires-Dist: logzero
Requires-Dist: requests
Requires-Dist: pycodestyle
